djangocms_dag_jetcode/__init__.py
djangocms_dag_jetcode/admin.py
djangocms_dag_jetcode/apps.py
djangocms_dag_jetcode/cms_plugins.py
djangocms_dag_jetcode/conf/__init__.py
djangocms_dag_jetcode/conf/settings.py
djangocms_dag_jetcode/locale/fr/LC_MESSAGES/django.mo
djangocms_dag_jetcode/locale/fr/LC_MESSAGES/django.po
djangocms_dag_jetcode/migrations/0001_initial.py
djangocms_dag_jetcode/migrations/0002_auto_20220610_1207.py
djangocms_dag_jetcode/migrations/__init__.py
djangocms_dag_jetcode/models.py
djangocms_dag_jetcode/static/djangocms_dag_jetcode/css/base.css
djangocms_dag_jetcode/static/djangocms_dag_jetcode/css/container.css
djangocms_dag_jetcode/static/djangocms_dag_jetcode/css/package.css
djangocms_dag_jetcode/static/djangocms_dag_jetcode/css/product.css
djangocms_dag_jetcode/static/djangocms_dag_jetcode/css/productselector.css
djangocms_dag_jetcode/static/djangocms_dag_jetcode/img/calendar-icon.png
djangocms_dag_jetcode/templates/djangocms_dag_jetcode/default.html
djangocms_dag_jetcode/urls.py
djangocms_dag_jetcode/views.py
djangocms_dag_jetcode-1.2.1.dist-info/LICENSE
djangocms_dag_jetcode-1.2.1.dist-info/WHEEL
djangocms_dag_jetcode-1.2.1.dist-info/METADATA
djangocms_dag_jetcode-1.2.1.dist-info/RECORD
