Metadata-Version: 2.1
Name: djangocms-dag-jetcode
Version: 1.2.1
Summary: Django CMS DAG Jetcode is a plugin for Django CMS that allows you to add DAG System's Jetcodes on your site.
Home-page: https://gitlab.com/kapt/open-source/djangocms-dag-jetcode
License: BSD-3-Clause
Author: Kapt dev team
Author-email: dev@kapt.mobi
Requires-Python: >=3.0.0,<4.0.0
Classifier: License :: OSI Approved :: BSD License
Classifier: Programming Language :: Python :: 3
Classifier: Programming Language :: Python :: 3.10
Classifier: Programming Language :: Python :: 3.4
Classifier: Programming Language :: Python :: 3.5
Classifier: Programming Language :: Python :: 3.6
Classifier: Programming Language :: Python :: 3.7
Classifier: Programming Language :: Python :: 3.8
Classifier: Programming Language :: Python :: 3.9
Requires-Dist: Django (>2)
Requires-Dist: django-cms (>=3.0.0,<4.0.0)
Requires-Dist: django-multiselectfield (>=0.1.12,<0.2.0)
Requires-Dist: djangocms-attributes-field (>=2.0.0,<3.0.0)
Project-URL: Repository, https://gitlab.com/kapt/open-source/djangocms-dag-jetcode
